langchain_objectbox/__init__.py
langchain_objectbox/objectbox-model.json
langchain_objectbox/vectorstores.py
langchain_objectbox-0.1.0a5.dist-info/LICENSE
langchain_objectbox-0.1.0a5.dist-info/METADATA
langchain_objectbox-0.1.0a5.dist-info/WHEEL
langchain_objectbox-0.1.0a5.dist-info/RECORD
